{"Last Update": {"Date": "12/04/2017", "Time": "08:41:19"}, "Operation Breakout Weapon Case": {"MP7 | Urban Hazard (Well-Worn)": "0.09", "P2000 | Ivory (Field-Tested)": "0.08", "StatTrak\u2122 Desert Eagle | Conspiracy (Minimal Wear)": "9.99", "CZ75-Auto | Tigris (Field-Tested)": "0.26", "UMP-45 | Labyrinth (Factory New)": "0.15", "UMP-45 | Labyrinth (Field-Tested)": "0.08", "Nova | Koi (Factory New)": "0.53", "Nova | Koi (Well-Worn)": 0, "StatTrak\u2122 P90 | Asiimov (Factory New)": "87.78", "SSG 08 | Abyss (Field-Tested)": "0.16", "StatTrak\u2122 Nova | Koi (Factory New)": "2.35", "Negev | Desert-Strike (Well-Worn)": "0.08", "StatTrak\u2122 UMP-45 | Labyrinth (Field-Tested)": "0.34", "Glock-18 | Water Elemental (Well-Worn)": "3.92", "P90 | Asiimov (Well-Worn)": "4.17", "StatTrak\u2122 UMP-45 | Labyrinth (Minimal Wear)": "0.51", "StatTrak\u2122 Five-SeveN | Fowl Play (Minimal Wear)": "5.17", "StatTrak\u2122 CZ75-Auto | Tigris (Field-Tested)": "0.99", "Desert Eagle | Conspiracy (Factory New)": "2.68", "P2000 | Ivory (Well-Worn)": "0.08", "StatTrak\u2122 CZ75-Auto | Tigris (Minimal Wear)": "1.48", "SSG 08 | Abyss (Factory New)": "1.36", "CZ75-Auto | Tigris (Factory New)": "1.14", "StatTrak\u2122 SSG 08 | Abyss (Well-Worn)": "0.47", "P90 | Asiimov (Factory New)": "16.21", "StatTrak\u2122 Glock-18 | Water Elemental (Factory New)": "27.99", "StatTrak\u2122 Glock-18 | Water Elemental (Minimal Wear)": "17.84", "M4A1-S | Cyrex (Minimal Wear)": "11.01", "StatTrak\u2122 CZ75-Auto | Tigris (Well-Worn)": "0.9", "StatTrak\u2122 P2000 | Ivory (Well-Worn)": "0.23", "StatTrak\u2122 PP-Bizon | Osiris (Factory New)": "2.55", "M4A1-S | Cyrex (Well-Worn)": "8.72", "StatTrak\u2122 Negev | Desert-Strike (Field-Tested)": "0.22", "StatTrak\u2122 P90 | Asiimov (Minimal Wear)": "30.84", "StatTrak\u2122 P2000 | Ivory (Factory New)": "1.08", "Desert Eagle | Conspiracy (Minimal Wear)": "2.09", "PP-Bizon | Osiris (Field-Tested)": "0.26", "Negev | Desert-Strike (Minimal Wear)": "0.08", "StatTrak\u2122 M4A1-S | Cyrex (Factory New)": "58.97", "Five-SeveN | Fowl Play (Factory New)": "2.69", "P90 | Asiimov (Minimal Wear)": "8.0", "M4A1-S | Cyrex (Factory New)": "14.37", "StatTrak\u2122 P2000 | Ivory (Minimal Wear)": "0.27", "StatTrak\u2122 Five-SeveN | Fowl Play (Field-Tested)": "3.11", "StatTrak\u2122 MP7 | Urban Hazard (Field-Tested)": "0.25", "P250 | Supernova (Well-Worn)": "0.43", "StatTrak\u2122 P90 | Asiimov (Field-Tested)": "13.88", "SSG 08 | Abyss (Well-Worn)": "0.14", "StatTrak\u2122 Negev | Desert-Strike (Minimal Wear)": "0.28", "P2000 | Ivory (Minimal Wear)": "0.08", "P250 | Supernova (Factory New)": "0.66", "Glock-18 | Water Elemental (Factory New)": "7.06", "StatTrak\u2122 Nova | Koi (Well-Worn)": 0, "Negev | Desert-Strike (Field-Tested)": "0.08", "Desert Eagle | Conspiracy (Well-Worn)": 0, "P2000 | Ivory (Factory New)": "0.17", "Glock-18 | Water Elemental (Minimal Wear)": "4.14", "Five-SeveN | Fowl Play (Minimal Wear)": "1.46", "StatTrak\u2122 M4A1-S | Cyrex (Minimal Wear)": "40.43", "Negev | Desert-Strike (Factory New)": "0.13", "SSG 08 | Abyss (Minimal Wear)": "0.29", "M4A1-S | Cyrex (Field-Tested)": "8.19", "P250 | Supernova (Field-Tested)": "0.33", "CZ75-Auto | Tigris (Well-Worn)": "0.26", "StatTrak\u2122 Glock-18 | Water Elemental (Well-Worn)": "14.31", "StatTrak\u2122 Glock-18 | Water Elemental (Field-Tested)": "10.37", "PP-Bizon | Osiris (Minimal Wear)": "0.33", "MP7 | Urban Hazard (Field-Tested)": "0.08", "Nova | Koi (Minimal Wear)": "0.32", "StatTrak\u2122 PP-Bizon | Osiris (Well-Worn)": "0.84", "UMP-45 | Labyrinth (Minimal Wear)": "0.09", "PP-Bizon | Osiris (Factory New)": "0.53", "StatTrak\u2122 Desert Eagle | Conspiracy (Well-Worn)": 0, "StatTrak\u2122 P250 | Supernova (Well-Worn)": "2.08", "Desert Eagle | Conspiracy (Field-Tested)": "1.98", "Five-SeveN | Fowl Play (Field-Tested)": "1.14", "StatTrak\u2122 Nova | Koi (Minimal Wear)": "1.24", "StatTrak\u2122 M4A1-S | Cyrex (Field-Tested)": "25.06", "StatTrak\u2122 Five-SeveN | Fowl Play (Well-Worn)": "2.93", "StatTrak\u2122 UMP-45 | Labyrinth (Factory New)": "0.97", "P250 | Supernova (Minimal Wear)": "0.36", "StatTrak\u2122 Nova | Koi (Field-Tested)": "0.95", "StatTrak\u2122 SSG 08 | Abyss (Factory New)": "6.38", "PP-Bizon | Osiris (Well-Worn)": "0.3", "Glock-18 | Water Elemental (Field-Tested)": "3.07", "StatTrak\u2122 UMP-45 | Labyrinth (Well-Worn)": "0.62", "MP7 | Urban Hazard (Factory New)": "0.13", "StatTrak\u2122 P2000 | Ivory (Field-Tested)": "0.22", "MP7 | Urban Hazard (Minimal Wear)": "0.1", "P90 | Asiimov (Field-Tested)": "4.5", "StatTrak\u2122 Five-SeveN | Fowl Play (Factory New)": "14.65", "StatTrak\u2122 PP-Bizon | Osiris (Field-Tested)": "0.87", "StatTrak\u2122 CZ75-Auto | Tigris (Factory New)": "5.01", "StatTrak\u2122 MP7 | Urban Hazard (Factory New)": "0.78", "Five-SeveN | Fowl Play (Well-Worn)": "1.15", "StatTrak\u2122 Desert Eagle | Conspiracy (Factory New)": "14.47", "Nova | Koi (Field-Tested)": "0.32", "StatTrak\u2122 M4A1-S | Cyrex (Well-Worn)": "27.01", "CZ75-Auto | Tigris (Minimal Wear)": "0.35", "StatTrak\u2122 SSG 08 | Abyss (Field-Tested)": "0.57", "StatTrak\u2122 Negev | Desert-Strike (Factory New)": "0.5", "StatTrak\u2122 MP7 | Urban Hazard (Minimal Wear)": "0.41", "StatTrak\u2122 P250 | Supernova (Factory New)": "3.12", "StatTrak\u2122 Negev | Desert-Strike (Well-Worn)": "0.22", "StatTrak\u2122 PP-Bizon | Osiris (Minimal Wear)": "1.37", "UMP-45 | Labyrinth (Well-Worn)": "0.11", "StatTrak\u2122 MP7 | Urban Hazard (Well-Worn)": "0.35", "StatTrak\u2122 P90 | Asiimov (Well-Worn)": "11.41", "StatTrak\u2122 Desert Eagle | Conspiracy (Field-Tested)": "7.19", "StatTrak\u2122 P250 | Supernova (Minimal Wear)": "1.88", "StatTrak\u2122 P250 | Supernova (Field-Tested)": "1.37", "StatTrak\u2122 SSG 08 | Abyss (Minimal Wear)": "1.28"}}